[
    {
        "Id": "Morgan Stanley",
        "Name": "Morgan Stanley",
        "ModuleType": "web",
        "Details": {
            "Url": "https://www.morganstanley.com",
            "IconUrl": "https://www.morganstanley.com/etc/designs/msdotcom/image/favicon-96x96.png"
        }
    },
    {
        "Id": "Microsoft",
        "Name": "Microsoft",
        "ModuleType": "web",
        "Details": {
            "Url": "https://www.microsoft.com",
            "IconUrl": "https://www.microsoft.com/favicon.ico?v2"
        }
    },
    {
        "Id": "Google",
        "Name": "Google",
        "ModuleType": "web",
        "Details": {
            "Url": "https://www.google.com",
            "IconUrl": "https://www.google.com/images/branding/googleg/1x/googleg_standard_color_128dp.png"
        }
    },
    {
        "Id": "FINOS FDC3 Workbench",
        "Name": "FINOS FDC3 Workbench",
        "ModuleType": "web",
        "Details": {
            "Url": "https://fdc3.finos.org/toolbox/fdc3-workbench/",
            "IconUrl": "https://fdc3.finos.org/toolbox/fdc3-workbench/favicon.ico"
        }
    }
]